adidnsdump/__init__.py
adidnsdump/dnsdump.py
adidnsdump-1.4.0.dist-info/licenses/LICENSE
adidnsdump-1.4.0.dist-info/METADATA
adidnsdump-1.4.0.dist-info/WHEEL
adidnsdump-1.4.0.dist-info/entry_points.txt
adidnsdump-1.4.0.dist-info/top_level.txt
adidnsdump-1.4.0.dist-info/RECORD
